groqpy/__init__.py
groqpy/groq_agent.py
groqpy-0.2.3.dist-info/LICENSE.txt
groqpy-0.2.3.dist-info/METADATA
groqpy-0.2.3.dist-info/WHEEL
groqpy-0.2.3.dist-info/top_level.txt
groqpy-0.2.3.dist-info/RECORD
