Metadata-Version: 2.1
Name: groqpy
Version: 0.2.3
Summary: A Python package.
License-File: LICENSE.txt
Requires-Dist: certifi~=2024.7.4
Requires-Dist: charset-normalizer~=3.3.2
Requires-Dist: idna~=3.7
Requires-Dist: requests~=2.32.3
Requires-Dist: urllib3~=2.2.2
